LICENSE.txt
MANIFEST.in
README.md
ncc
ncc-capture-schema
ncc-get-all-schema
ncc-get-schema
ncc-yang-push
pyproject.toml
setup.cfg
setup.py
versioneer.py
ncc.egg-info/PKG-INFO
ncc.egg-info/SOURCES.txt
ncc.egg-info/dependency_links.txt
ncc.egg-info/requires.txt
ncc.egg-info/top_level.txt
nccutil/__init__.py
nccutil/_version.py
nccutil/repoutil.py