Metadata-Version: 1.1
Name: ncc
Version: 0.3.1
Summary: A set of NETCONF/YANG-focused scripts using ncclient
Home-page: https://github.com/CiscoDevNet/ncc
Author: Einar Nilsen-Nygaard
Author-email: einarnn@cisco.com
License: Apache 2.0; Copyright (c) 2018 Cisco and/or its affiliates.
Download-URL: https://pypi.python.org/pypi/ncc
Keywords: yang,netconf
Platform: UNKNOWN
Classifier: Development Status :: 4 - Beta
Classifier: Intended Audience :: Developers
Classifier: Natural Language :: English
Classifier: License :: OSI Approved :: Apache Software License
Classifier: Programming Language :: Python :: 2
Classifier: Programming Language :: Python :: 2.7
Classifier: Programming Language :: Python :: 3
Classifier: Programming Language :: Python :: 3.5
Classifier: Programming Language :: Python :: 3.6
